{
  "input": "data/replication/anonymous_fingerprints.json",
  "records": 60,
  "participants": 10,
  "collections_per_participant": {
    "participant_001": 6,
    "participant_002": 6,
    "participant_003": 6,
    "participant_004": 6,
    "participant_005": 6,
    "participant_006": 6,
    "participant_007": 6,
    "participant_008": 6,
    "participant_009": 6,
    "participant_010": 6
  },
  "feature_mode": "automatic",
  "selected_features": [
    "audio",
    "canvas",
    "fontPreferences",
    "languages",
    "platform",
    "timezone",
    "vendorFlavors",
    "webGlBasics",
    "webGlExtensions"
  ],
  "max_duration_ms": 100.0,
  "p_max": 0.5,
  "max_neighbors": 9,
  "evaluation": "leave-one-out",
  "classifier": "KNeighborsClassifier",
  "metric": "euclidean",
  "selection_method": "regras_metodologicas_do_artigo",
  "automatic_selection_has_fixed_feature_limit": false
}